<?xml version="1.0" encoding="utf-8"?>
<TextureAtlas imagePath="ship.png">
	<!-- Created with Adobe Animate version 19.2.1.408 -->
	<!-- http://www.adobe.com/products/animate.html -->
	<SubTexture name="cannon instance 10000" x="1" y="1" width="47" height="42" pivotX="23" pivotY="20.65"/>
	<SubTexture name="redShip instance 10000" x="49" y="1" width="113" height="67" pivotX="56.65" pivotY="32.9"/>
	<SubTexture name="redShip instance 10001" x="1" y="69" width="113" height="67"/>
	<SubTexture name="redShip instance 10002" x="1" y="69" width="113" height="67"/>
	<SubTexture name="redShip instance 10003" x="1" y="69" width="113" height="67"/>
	<SubTexture name="redShip instance 10004" x="1" y="69" width="113" height="67"/>
	<SubTexture name="redShip instance 10005" x="1" y="69" width="113" height="67"/>
	<SubTexture name="redShip instance 10006" x="115" y="69" width="113" height="67"/>
	<SubTexture name="redShip instance 10007" x="115" y="69" width="113" height="67"/>
	<SubTexture name="redShip instance 10008" x="115" y="69" width="113" height="67"/>
	<SubTexture name="redShip instance 10009" x="115" y="69" width="113" height="67"/>
	<SubTexture name="redShip instance 10010" x="115" y="69" width="113" height="67"/>
	<SubTexture name="redShip instance 10011" x="1" y="137" width="113" height="67"/>
	<SubTexture name="redShip instance 10012" x="115" y="69" width="113" height="67"/>
	<SubTexture name="redShip instance 10013" x="115" y="69" width="113" height="67"/>
	<SubTexture name="redShip instance 10014" x="115" y="69" width="113" height="67"/>
	<SubTexture name="redShip instance 10015" x="115" y="69" width="113" height="67"/>
	<SubTexture name="redShip instance 10016" x="1" y="69" width="113" height="67"/>
	<SubTexture name="redShip instance 10017" x="1" y="69" width="113" height="67"/>
	<SubTexture name="redShip instance 10018" x="1" y="69" width="113" height="67"/>
	<SubTexture name="redShip instance 10019" x="49" y="1" width="113" height="67"/>
</TextureAtlas>
